quickumls/__init__.py
quickumls/about.py
quickumls/client.py
quickumls/constants.py
quickumls/core.py
quickumls/install.py
quickumls/network.py
quickumls/server.py
quickumls/spacy_component.py
quickumls/toolbox.py
quickumls-1.4.2.dist-info/LICENSE.txt
quickumls-1.4.2.dist-info/METADATA
quickumls-1.4.2.dist-info/WHEEL
quickumls-1.4.2.dist-info/top_level.txt
quickumls-1.4.2.dist-info/RECORD
