Metadata-Version: 2.1
Name: quickumls
Version: 1.4.2
Summary: QuickUMLS is a tool for fast, unsupervised biomedical concept extraction from medical text
Home-page: https://github.com/Georgetown-IR-Lab/QuickUMLS
Author: Luca Soldaini
Author-email: luca@soldaini.net
License: MIT
Classifier: Programming Language :: Python :: 3
Classifier: Programming Language :: Python :: 2
Classifier: License :: OSI Approved :: MIT License
Classifier: Operating System :: OS Independent
Classifier: Development Status :: 5 - Production/Stable
Classifier: Topic :: Scientific/Engineering :: Artificial Intelligence
Classifier: Topic :: Scientific/Engineering :: Bio-Informatics
License-File: LICENSE.txt
Requires-Dist: leveldb >=0.193
Requires-Dist: numpy >=1.8.2
Requires-Dist: spacy >=3.0.6
Requires-Dist: unidecode >=0.4.19
Requires-Dist: nltk >=3.3
Requires-Dist: quickumls-simstring >=1.1.5r1
Requires-Dist: unqlite >=0.8.1
Requires-Dist: six
